[{
  "_id": {
    "$oid": "6584887b33b50f39862933b4"
  },
  "name": "Casimir",
  "profile": "https://cloudflare-ipfs.com/ipfs/Qmd3W5DuhgHirLHGVixi6V76LhCkZUz6pnFt5AJBiyvHye/avatar/761.jpg",
  "gender": "female",
  "dob": "1988-04-07T03:17:13.432Z",
  "bio": "Sit consectetur corrupti distinctio atque possimus."
},
{
  "_id": {
    "$oid": "6584887b33b50f39862933b5"
  },
  "name": "Yasmeen",
  "profile": "https://cloudflare-ipfs.com/ipfs/Qmd3W5DuhgHirLHGVixi6V76LhCkZUz6pnFt5AJBiyvHye/avatar/385.jpg",
  "gender": "male",
  "dob": "1946-09-19T18:34:26.720Z",
  "bio": "Vitae doloremque ab dolores harum."
},
{
  "_id": {
    "$oid": "6584887b33b50f39862933b6"
  },
  "name": "Ludie",
  "profile": "https://cloudflare-ipfs.com/ipfs/Qmd3W5DuhgHirLHGVixi6V76LhCkZUz6pnFt5AJBiyvHye/avatar/483.jpg",
  "gender": "female",
  "dob": "1978-06-13T12:32:58.879Z",
  "bio": "Mollitia cumque iure placeat assumenda recusandae sunt libero sapiente corrupti."
},
{
  "_id": {
    "$oid": "6584887b33b50f39862933b7"
  },
  "name": "Waylon",
  "profile": "https://cloudflare-ipfs.com/ipfs/Qmd3W5DuhgHirLHGVixi6V76LhCkZUz6pnFt5AJBiyvHye/avatar/202.jpg",
  "gender": "male",
  "dob": "1965-09-20T16:30:31.134Z",
  "bio": "Nobis sunt tempore rerum est."
},
{
  "_id": {
    "$oid": "6584887b33b50f39862933b8"
  },
  "name": "Gideon",
  "profile": "https://cloudflare-ipfs.com/ipfs/Qmd3W5DuhgHirLHGVixi6V76LhCkZUz6pnFt5AJBiyvHye/avatar/235.jpg",
  "gender": "female",
  "dob": "2004-08-30T10:22:53.243Z",
  "bio": "Ullam eius earum dolorum."
},
{
  "_id": {
    "$oid": "6584887b33b50f39862933b9"
  },
  "name": "Mac",
  "profile": "https://cloudflare-ipfs.com/ipfs/Qmd3W5DuhgHirLHGVixi6V76LhCkZUz6pnFt5AJBiyvHye/avatar/288.jpg",
  "gender": "female",
  "dob": "1962-01-21T16:25:51.167Z",
  "bio": "Officia quaerat atque quo maiores."
},
{
  "_id": {
    "$oid": "6584887b33b50f39862933ba"
  },
  "name": "Austen",
  "profile": "https://cloudflare-ipfs.com/ipfs/Qmd3W5DuhgHirLHGVixi6V76LhCkZUz6pnFt5AJBiyvHye/avatar/589.jpg",
  "gender": "male",
  "dob": "1998-04-29T06:44:32.991Z",
  "bio": "Reiciendis laboriosam iure est."
},
{
  "_id": {
    "$oid": "6584887b33b50f39862933bb"
  },
  "name": "Dylan",
  "profile": "https://cloudflare-ipfs.com/ipfs/Qmd3W5DuhgHirLHGVixi6V76LhCkZUz6pnFt5AJBiyvHye/avatar/1098.jpg",
  "gender": "female",
  "dob": "1948-12-27T09:38:18.529Z",
  "bio": "Doloribus praesentium pariatur expedita quas."
},
{
  "_id": {
    "$oid": "6584887b33b50f39862933bc"
  },
  "name": "Jessie",
  "profile": "https://cloudflare-ipfs.com/ipfs/Qmd3W5DuhgHirLHGVixi6V76LhCkZUz6pnFt5AJBiyvHye/avatar/1162.jpg",
  "gender": "male",
  "dob": "1965-07-04T07:59:20.794Z",
  "bio": "Quis beatae esse dolorum error error nihil qui a."
},
{
  "_id": {
    "$oid": "6584887b33b50f39862933bd"
  },
  "name": "Caleb",
  "profile": "https://cloudflare-ipfs.com/ipfs/Qmd3W5DuhgHirLHGVixi6V76LhCkZUz6pnFt5AJBiyvHye/avatar/69.jpg",
  "gender": "male",
  "dob": "1995-05-23T20:07:49.624Z",
  "bio": "Maxime dolores sunt sit perspiciatis rerum est laboriosam numquam consectetur."
},
{
  "_id": {
    "$oid": "6584887b33b50f39862933be"
  },
  "name": "Vella",
  "profile": "https://cloudflare-ipfs.com/ipfs/Qmd3W5DuhgHirLHGVixi6V76LhCkZUz6pnFt5AJBiyvHye/avatar/210.jpg",
  "gender": "female",
  "dob": "1984-05-18T23:24:20.789Z",
  "bio": "Doloribus facilis ipsam nesciunt reiciendis rem corrupti a natus nostrum."
},
{
  "_id": {
    "$oid": "6584887b33b50f39862933bf"
  },
  "name": "Amani",
  "profile": "https://cloudflare-ipfs.com/ipfs/Qmd3W5DuhgHirLHGVixi6V76LhCkZUz6pnFt5AJBiyvHye/avatar/695.jpg",
  "gender": "female",
  "dob": "1953-09-29T22:23:03.814Z",
  "bio": "Amet repudiandae reprehenderit magni."
},
{
  "_id": {
    "$oid": "6584887b33b50f39862933c0"
  },
  "name": "Rossie",
  "profile": "https://cloudflare-ipfs.com/ipfs/Qmd3W5DuhgHirLHGVixi6V76LhCkZUz6pnFt5AJBiyvHye/avatar/882.jpg",
  "gender": "female",
  "dob": "1994-08-20T18:31:31.026Z",
  "bio": "Fugit iure doloremque totam itaque vitae sit error magnam."
},
{
  "_id": {
    "$oid": "6584887b33b50f39862933c1"
  },
  "name": "Emelie",
  "profile": "https://cloudflare-ipfs.com/ipfs/Qmd3W5DuhgHirLHGVixi6V76LhCkZUz6pnFt5AJBiyvHye/avatar/930.jpg",
  "gender": "female",
  "dob": "1992-04-03T07:10:38.661Z",
  "bio": "Blanditiis quisquam eveniet."
},
{
  "_id": {
    "$oid": "6584887b33b50f39862933c2"
  },
  "name": "Noah",
  "profile": "https://cloudflare-ipfs.com/ipfs/Qmd3W5DuhgHirLHGVixi6V76LhCkZUz6pnFt5AJBiyvHye/avatar/108.jpg",
  "gender": "male",
  "dob": "2004-11-02T23:16:58.582Z",
  "bio": "Architecto est quam suscipit excepturi sequi placeat."
},
{
  "_id": {
    "$oid": "6584887b33b50f39862933c3"
  },
  "name": "Gerson",
  "profile": "https://cloudflare-ipfs.com/ipfs/Qmd3W5DuhgHirLHGVixi6V76LhCkZUz6pnFt5AJBiyvHye/avatar/337.jpg",
  "gender": "male",
  "dob": "1987-05-24T05:12:28.040Z",
  "bio": "Praesentium repellat ab voluptatum nobis vero placeat at necessitatibus illum."
},
{
  "_id": {
    "$oid": "6584887b33b50f39862933c4"
  },
  "name": "Andre",
  "profile": "https://cloudflare-ipfs.com/ipfs/Qmd3W5DuhgHirLHGVixi6V76LhCkZUz6pnFt5AJBiyvHye/avatar/1210.jpg",
  "gender": "male",
  "dob": "2003-06-06T23:03:32.826Z",
  "bio": "Beatae perspiciatis temporibus repellat tenetur modi mollitia."
},
{
  "_id": {
    "$oid": "6584887b33b50f39862933c5"
  },
  "name": "Grace",
  "profile": "https://cloudflare-ipfs.com/ipfs/Qmd3W5DuhgHirLHGVixi6V76LhCkZUz6pnFt5AJBiyvHye/avatar/1066.jpg",
  "gender": "female",
  "dob": "1995-01-06T20:53:40.157Z",
  "bio": "Voluptate veniam harum quam unde delectus ducimus cumque aliquid."
},
{
  "_id": {
    "$oid": "6584887b33b50f39862933c6"
  },
  "name": "Jadyn",
  "profile": "https://cloudflare-ipfs.com/ipfs/Qmd3W5DuhgHirLHGVixi6V76LhCkZUz6pnFt5AJBiyvHye/avatar/1222.jpg",
  "gender": "female",
  "dob": "1984-12-08T04:09:23.213Z",
  "bio": "At nemo necessitatibus iusto magnam earum reprehenderit odio nobis."
},
{
  "_id": {
    "$oid": "6584887b33b50f39862933c7"
  },
  "name": "Cecile",
  "profile": "https://cloudflare-ipfs.com/ipfs/Qmd3W5DuhgHirLHGVixi6V76LhCkZUz6pnFt5AJBiyvHye/avatar/414.jpg",
  "gender": "female",
  "dob": "1944-05-16T21:12:35.306Z",
  "bio": "Enim tempore modi impedit necessitatibus consectetur asperiores impedit."
}]